anki_compressor/__init__.py
anki_compressor/__main__.py
anki_compressor-0.1.0.dist-info/LICENSE
anki_compressor-0.1.0.dist-info/METADATA
anki_compressor-0.1.0.dist-info/WHEEL
anki_compressor-0.1.0.dist-info/entry_points.txt
anki_compressor-0.1.0.dist-info/top_level.txt
anki_compressor-0.1.0.dist-info/RECORD
