Metadata-Version: 2.1
Name: anki-compressor
Version: 0.1.0
Summary: Compress Anki deck .apkg file size
Home-page: https://github.com/pjsier/anki-compressor
Author: Patrick Sier
License: MIT
Project-URL: Bug Reports, https://github.com/pjsier/anki-compressor/issues
Project-URL: Source, https://github.com/pjsier/anki-compressor
Platform: UNKNOWN
Classifier: Development Status :: 3 - Alpha
Classifier: License :: OSI Approved :: MIT License
Classifier: Programming Language :: Python :: 3.6
Requires-Dist: Pillow
Requires-Dist: pydub
Requires-Dist: tqdm
